ThermiaOnlineAPI/__init__.py
ThermiaOnlineAPI/const.py
ThermiaOnlineAPI/api/ThermiaAPI.py
ThermiaOnlineAPI/api/__init__.py
ThermiaOnlineAPI/exceptions/AuthenticationException.py
ThermiaOnlineAPI/exceptions/NetworkException.py
ThermiaOnlineAPI/exceptions/__init__.py
ThermiaOnlineAPI/model/HeatPump.py
ThermiaOnlineAPI/model/__init__.py
ThermiaOnlineAPI/utils/__init__.py
ThermiaOnlineAPI/utils/utils.py
ThermiaOnlineAPI-6.3.1.dist-info/LICENSE
ThermiaOnlineAPI-6.3.1.dist-info/METADATA
ThermiaOnlineAPI-6.3.1.dist-info/WHEEL
ThermiaOnlineAPI-6.3.1.dist-info/top_level.txt
ThermiaOnlineAPI-6.3.1.dist-info/RECORD
