Metadata-Version: 2.1
Name: ThermiaOnlineAPI
Version: 6.3.1
Summary: A Python API for Thermia heat pumps using https://online.thermia.se
Home-page: https://github.com/klejejs/python-thermia-online-api
Download-URL: https://github.com/klejejs/python-thermia-online-api/releases
Author: Krisjanis Lejejs
Author-email: krisjanis.lejejs@gmail.com
License: GPL-3.0
Keywords: Thermia,Online
License-File: LICENSE
